tree_format/__init__.py
tree_format/_text.py
tree_format/tests/__init__.py
tree_format/tests/test_text.py
tree_format-0.1.1.dist-info/DESCRIPTION.rst
tree_format-0.1.1.dist-info/METADATA
tree_format-0.1.1.dist-info/RECORD
tree_format-0.1.1.dist-info/WHEEL
tree_format-0.1.1.dist-info/metadata.json
tree_format-0.1.1.dist-info/top_level.txt
