Metadata-Version: 2.0
Name: tree-format
Version: 0.1.1
Summary: UNKNOWN
Home-page: http://github.com/jml/tree-format
Author: Jonathan M. Lange
Author-email: jml@mumak.net
License: UNKNOWN
Platform: UNKNOWN
Classifier: Intended Audience :: Developers
Classifier: License :: OSI Approved :: Apache Software License
Classifier: License :: OSI Approved :: BSD License
Classifier: Operating System :: OS Independent
Classifier: Programming Language :: Python
Classifier: Programming Language :: Python :: 2
Classifier: Programming Language :: Python :: 2.7
Classifier: Programming Language :: Python :: Implementation :: CPython
Classifier: Programming Language :: Python :: Implementation :: PyPy
Provides-Extra: dev
Requires-Dist: pytest (>=2.7.1); extra == 'dev'
Requires-Dist: testtools (>=1.8.0); extra == 'dev'
